rolv/__init__.py
rolv/apps.py
rolv/config.py
rolv/disk.py
rolv/executables.py
rolv/lib.py
rolv/package.py
rolv/rc.py
rolv/src/version
rolv/src/apps/fzf/.fzf.bash
rolv/src/apps/fzf/.fzf.zsh
rolv/src/apps/fzf/bin/fzf
rolv/src/apps/fzf/bin/fzf-tmux
rolv/src/apps/fzf/doc/fzf.txt
rolv/src/apps/fzf/man/man1/fzf-tmux.1
rolv/src/apps/fzf/man/man1/fzf.1
rolv/src/apps/fzf/plugin/fzf.vim
rolv/src/apps/fzf/shell/completion.bash
rolv/src/apps/fzf/shell/completion.zsh
rolv/src/apps/fzf/shell/key-bindings.bash
rolv/src/apps/fzf/shell/key-bindings.fish
rolv/src/apps/fzf/shell/key-bindings.zsh
rolv/src/config/default_aliases_and_functions
rolv/src/executables/gitc
rolv/src/executables/readme.md
rolv-0.0.5.dist-info/METADATA
rolv-0.0.5.dist-info/WHEEL
rolv-0.0.5.dist-info/entry_points.txt
rolv-0.0.5.dist-info/top_level.txt
rolv-0.0.5.dist-info/RECORD
